LICENSE
MANIFEST.in
README.md
requirements.txt
setup.py
bloxs/__init__.py
bloxs/bloxs.py
bloxs.egg-info/PKG-INFO
bloxs.egg-info/SOURCES.txt
bloxs.egg-info/dependency_links.txt
bloxs.egg-info/requires.txt
bloxs.egg-info/top_level.txt
bloxs/js_dist/chart.3.7.1.min.js