Metadata-Version: 2.1
Name: bloxs
Version: 1.0.2
Summary: Display data in an attractive way
Home-page: https://github.com/mljar/bloxs
Author: MLJAR, Sp. z o.o.
Author-email: contact@mljar.com
License: Apache License 2.0
Keywords: data science,jupyter notebook,data analytics,dashboard,mljar
Platform: UNKNOWN
Classifier: Programming Language :: Python
License-File: LICENSE
